superannotate_databricks_connector/__init__.py
superannotate_databricks_connector/text.py
superannotate_databricks_connector/vector.py
superannotate_databricks_connector/schemas/__init__.py
superannotate_databricks_connector/schemas/comment.py
superannotate_databricks_connector/schemas/shapes.py
superannotate_databricks_connector/schemas/tag.py
superannotate_databricks_connector/schemas/text_schema.py
superannotate_databricks_connector/schemas/vector_schema.py
superannotate_databricks_connector/schemas/video_schema.py
superannotate_databricks_connector-0.0.1.dist-info/LICENSE.txt
superannotate_databricks_connector-0.0.1.dist-info/METADATA
superannotate_databricks_connector-0.0.1.dist-info/WHEEL
superannotate_databricks_connector-0.0.1.dist-info/top_level.txt
superannotate_databricks_connector-0.0.1.dist-info/RECORD
