Metadata-Version: 2.1
Name: superannotate-databricks-connector
Version: 0.0.1
Summary: Custom functions to work with SuperAnnotate in Databricks
Author-email: Leo Lindén <leo@superannotate.com>
Maintainer-email: Leo Lindén <leo@superannotate.com>
License: MIT License
Project-URL: Homepage, https://github.com/superannotateai/superannotate-databricks-connector
Project-URL: Bug Reports, https://github.com/superannotateai/superannotate-databricks-connector/issues
Project-URL: Source, https://github.com/superannotateai/superannotate-databricks-connector/
Keywords: superannotate_databricks_connector,superannotate
Classifier: Intended Audience :: Developers
Classifier: Topic :: Software Development :: Build Tools
Classifier: Programming Language :: Python :: 3
Classifier: Programming Language :: Python :: 3.8
Classifier: Programming Language :: Python :: 3.9
Classifier: Programming Language :: Python :: 3.10
Classifier: Programming Language :: Python :: 3.11
Classifier: Programming Language :: Python :: 3 :: Only
Requires-Python: >=3.8
License-File: LICENSE.txt
Requires-Dist: pyspark (~=3.4.0)
Provides-Extra: test
Requires-Dist: pytest ; extra == 'test'
